rio_tiler/__init__.py
rio_tiler/colormap.py
rio_tiler/constants.py
rio_tiler/errors.py
rio_tiler/expression.py
rio_tiler/logger.py
rio_tiler/models.py
rio_tiler/profiles.py
rio_tiler/py.typed
rio_tiler/reader.py
rio_tiler/tasks.py
rio_tiler/types.py
rio_tiler/utils.py
rio_tiler/cmap_data/__init__.py
rio_tiler/cmap_data/accent.npy
rio_tiler/cmap_data/accent_r.npy
rio_tiler/cmap_data/afmhot.npy
rio_tiler/cmap_data/afmhot_r.npy
rio_tiler/cmap_data/algae.npy
rio_tiler/cmap_data/algae_r.npy
rio_tiler/cmap_data/amp.npy
rio_tiler/cmap_data/amp_r.npy
rio_tiler/cmap_data/autumn.npy
rio_tiler/cmap_data/autumn_r.npy
rio_tiler/cmap_data/balance.npy
rio_tiler/cmap_data/balance_r.npy
rio_tiler/cmap_data/binary.npy
rio_tiler/cmap_data/binary_r.npy
rio_tiler/cmap_data/blues.npy
rio_tiler/cmap_data/blues_r.npy
rio_tiler/cmap_data/bone.npy
rio_tiler/cmap_data/bone_r.npy
rio_tiler/cmap_data/brbg.npy
rio_tiler/cmap_data/brbg_r.npy
rio_tiler/cmap_data/brg.npy
rio_tiler/cmap_data/brg_r.npy
rio_tiler/cmap_data/bugn.npy
rio_tiler/cmap_data/bugn_r.npy
rio_tiler/cmap_data/bupu.npy
rio_tiler/cmap_data/bupu_r.npy
rio_tiler/cmap_data/bwr.npy
rio_tiler/cmap_data/bwr_r.npy
rio_tiler/cmap_data/cfastie.npy
rio_tiler/cmap_data/cividis.npy
rio_tiler/cmap_data/cividis_r.npy
rio_tiler/cmap_data/cmrmap.npy
rio_tiler/cmap_data/cmrmap_r.npy
rio_tiler/cmap_data/cool.npy
rio_tiler/cmap_data/cool_r.npy
rio_tiler/cmap_data/coolwarm.npy
rio_tiler/cmap_data/coolwarm_r.npy
rio_tiler/cmap_data/copper.npy
rio_tiler/cmap_data/copper_r.npy
rio_tiler/cmap_data/cubehelix.npy
rio_tiler/cmap_data/cubehelix_r.npy
rio_tiler/cmap_data/curl.npy
rio_tiler/cmap_data/curl_r.npy
rio_tiler/cmap_data/dark2.npy
rio_tiler/cmap_data/dark2_r.npy
rio_tiler/cmap_data/deep.npy
rio_tiler/cmap_data/deep_r.npy
rio_tiler/cmap_data/delta.npy
rio_tiler/cmap_data/delta_r.npy
rio_tiler/cmap_data/dense.npy
rio_tiler/cmap_data/dense_r.npy
rio_tiler/cmap_data/diff.npy
rio_tiler/cmap_data/diff_r.npy
rio_tiler/cmap_data/flag.npy
rio_tiler-8.0.5.dist-info/METADATA
rio_tiler-8.0.5.dist-info/WHEEL
rio_tiler-8.0.5.dist-info/licenses/AUTHORS.txt
rio_tiler-8.0.5.dist-info/licenses/LICENSE
rio_tiler-8.0.5.dist-info/RECORD
