Metadata-Version: 2.4
Name: rio-tiler
Version: 8.0.5
Summary: User friendly Rasterio plugin to read raster datasets.
Project-URL: Homepage, https://cogeotiff.github.io/rio-tiler/
Project-URL: Documentation, https://cogeotiff.github.io/rio-tiler/
Project-URL: Issues, https://github.com/cogeotiff/rio-tiler/issues
Project-URL: Source, https://github.com/cogeotiff/rio-tiler
Project-URL: Changelog, https://cogeotiff.github.io/rio-tiler/release-notes/
Author-email: Vincent Sarago <vincent@developmentseed.com>
License: BSD 3-Clause License
License-File: AUTHORS.txt
License-File: LICENSE
Keywords: COGEO,Cloud Optimized Geotiff,STAC,rasterio,slippy-map
Classifier: Intended Audience :: Information Technology
Classifier: Intended Audience :: Science/Research
Classifier: License :: OSI Approved :: BSD License
Classifier: Programming Language :: Python :: 3.11
Classifier: Programming Language :: Python :: 3.12
Classifier: Programming Language :: Python :: 3.13
Classifier: Programming Language :: Python :: 3.14
Classifier: Topic :: Scientific/Engineering :: GIS
Requires-Python: >=3.11
Requires-Dist: attrs
Requires-Dist: cachetools
Requires-Dist: color-operations
Requires-Dist: httpx
Requires-Dist: morecantile<8.0,>=5.0
Requires-Dist: numexpr
Requires-Dist: numpy
Requires-Dist: pydantic~=2.0
Requires-Dist: pystac<2.0,>=1.9
Requires-Dist: rasterio>=1.4.0
Requires-Dist: typing-extensions
Provides-Extra: s3
Requires-Dist: boto3; extra == 's3'
Provides-Extra: xarray
Requires-Dist: rioxarray; extra == 'xarray'
Requires-Dist: xarray; extra == 'xarray'
Provides-Extra: zarr
Requires-Dist: obstore; extra == 'zarr'
Requires-Dist: zarr~=3.0; extra == 'zarr'
